AUTHORS.rst
CODE_OF_CONDUCT.rst
Changelog.rst
LICENSE
MANIFEST.in
README.rst
setup.cfg
setup.py
artwork/LICENSE
artwork/banner-alt1.png
artwork/banner-alt2.png
artwork/favicon.ico
artwork/logo.png
docs/Makefile
docs/authors.rst
docs/changelog.rst
docs/conf.py
docs/contributing.rst
docs/copyright.rst
docs/faq.rst
docs/glossary.rst
docs/index.rst
docs/introduction.rst
docs/make.bat
docs/spelling_wordlist.txt
docs/_build/apicheck/apicheck.pickle
docs/_build/configcheck/configcheck.pickle
docs/_build/doctrees/authors.doctree
docs/_build/doctrees/changelog.doctree
docs/_build/doctrees/contributing.doctree
docs/_build/doctrees/copyright.doctree
docs/_build/doctrees/environment.pickle
docs/_build/doctrees/faq.doctree
docs/_build/doctrees/glossary.doctree
docs/_build/doctrees/index.doctree
docs/_build/doctrees/introduction.doctree
docs/_build/doctrees/developerguide/index.doctree
docs/_build/doctrees/developerguide/overview.doctree
docs/_build/doctrees/developerguide/partition_assignor.doctree
docs/_build/doctrees/history/changelog-0.9.doctree
docs/_build/doctrees/history/changelog-1.0.doctree
docs/_build/doctrees/history/changelog-1.1.doctree
docs/_build/doctrees/history/changelog-1.2.doctree
docs/_build/doctrees/history/changelog-1.3.doctree
docs/_build/doctrees/history/changelog-1.4.doctree
docs/_build/doctrees/history/changelog-1.5.doctree
docs/_build/doctrees/history/changelog-1.6.doctree
docs/_build/doctrees/history/changelog-1.7.doctree
docs/_build/doctrees/history/changelog-1.8.doctree
docs/_build/doctrees/history/index.doctree
docs/_build/doctrees/playbooks/cheatsheet.doctree
docs/_build/doctrees/playbooks/index.doctree
docs/_build/doctrees/playbooks/leaderelection.doctree
docs/_build/doctrees/playbooks/pageviews.doctree
docs/_build/doctrees/playbooks/quickstart.doctree
docs/_build/doctrees/playbooks/vscelery.doctree
docs/_build/doctrees/playbooks/vskafka.doctree
docs/_build/doctrees/reference/faust.agents.actor.doctree
test_faust_streaming.egg-info/PKG-INFO
test_faust_streaming.egg-info/SOURCES.txt
test_faust_streaming.egg-info/dependency_links.txt
test_faust_streaming.egg-info/entry_points.txt
test_faust_streaming.egg-info/not-zip-safe
test_faust_streaming.egg-info/requires.txt
test_faust_streaming.egg-info/top_level.txt